{
	"total": 7530,
	"list": [
		{
			"id": 225302312,
			"period": 702016,
			"date": "2018-09-04 10:01:30",
			"result": "10,4,5,1,7,3,9,6,2,8",
			"year": 2018
		}, {
			"id": 225301286,
			"period": 702015,
			"date": "2018-09-04 09:56:30",
			"result": "9,3,1,4,8,5,7,10,2,6",
			"year": 2018
		}, {
			"id": 225300516,
			"period": 702014,
			"date": "2018-09-04 09:51:30",
			"result": "6,9,8,1,5,7,2,3,10,4",
			"year": 2018
		}, {
			"id": 225302155,
			"period": 702013,
			"date": "2018-09-04 09:46:30",
			"result": "6,2,9,1,3,8,7,5,10,4",
			"year": 2018
		}, {
			"id": 225301635,
			"period": 702012,
			"date": "2018-09-04 09:41:30",
			"result": "1,4,10,9,6,7,8,2,5,3",
			"year": 2018
		}, {
			"id": 225299002,
			"period": 702011,
			"date": "2018-09-04 09:36:30",
			"result": "2,7,1,6,8,9,5,4,3,10",
			"year": 2018
		}, {
			"id": 225302468,
			"period": 702010,
			"date": "2018-09-04 09:31:30",
			"result": "5,2,1,4,7,10,9,3,6,8",
			"year": 2018
		}, {
			"id": 225301894,
			"period": 702009,
			"date": "2018-09-04 09:26:30",
			"result": "9,1,3,4,10,5,8,2,7,6",
			"year": 2018
		}, {
			"id": 225299181,
			"period": 702008,
			"date": "2018-09-04 09:21:30",
			"result": "9,2,5,1,7,4,3,10,8,6",
			"year": 2018
		}, {
			"id": 225302892,
			"period": 702007,
			"date": "2018-09-04 09:16:30",
			"result": "9,6,1,2,3,5,10,8,7,4",
			"year": 2018
		}, {
			"id": 225300453,
			"period": 702006,
			"date": "2018-09-04 09:11:30",
			"result": "7,3,5,4,8,10,9,2,6,1",
			"year": 2018
		}, {
			"id": 225299351,
			"period": 702005,
			"date": "2018-09-04 09:06:30",
			"result": "7,9,1,6,2,8,3,10,4,5",
			"year": 2018
		}, {
			"id": 224840537,
			"period": 702004,
			"date": "2018-09-03 23:56:30",
			"result": "10,1,5,6,2,8,9,3,7,4",
			"year": 2018
		}, {
			"id": 224838072,
			"period": 702003,
			"date": "2018-09-03 23:51:30",
			"result": "1,4,8,9,6,5,2,3,10,7",
			"year": 2018
		}, {
			"id": 224837244,
			"period": 702002,
			"date": "2018-09-03 23:46:30",
			"result": "3,10,4,8,2,1,6,9,7,5",
			"year": 2018
		}, {
			"id": 224839154,
			"period": 702001,
			"date": "2018-09-03 23:41:30",
			"result": "5,3,7,6,8,4,10,1,2,9",
			"year": 2018
		}, {
			"id": 224837819,
			"period": 702000,
			"date": "2018-09-03 23:36:30",
			"result": "5,7,4,9,6,2,3,1,8,10",
			"year": 2018
		}, {
			"id": 224837483,
			"period": 701999,
			"date": "2018-09-03 23:31:30",
			"result": "10,5,7,9,3,4,1,2,6,8",
			"year": 2018
		}, {
			"id": 224838880,
			"period": 701998,
			"date": "2018-09-03 23:26:30",
			"result": "1,5,4,2,8,7,6,3,9,10",
			"year": 2018
		}, {
			"id": 224838597,
			"period": 701997,
			"date": "2018-09-03 23:21:30",
			"result": "3,8,10,9,7,5,4,2,1,6",
			"year": 2018
		}, {
			"id": 224839943,
			"period": 701996,
			"date": "2018-09-03 23:16:30",
			"result": "9,3,7,1,10,5,8,4,6,2",
			"year": 2018
		}, {
			"id": 224839046,
			"period": 701995,
			"date": "2018-09-03 23:11:30",
			"result": "1,4,7,2,6,10,3,9,5,8",
			"year": 2018
		}, {
			"id": 224838251,
			"period": 701994,
			"date": "2018-09-03 23:06:30",
			"result": "1,7,6,3,8,9,2,4,5,10",
			"year": 2018
		}, {
			"id": 224840127,
			"period": 701993,
			"date": "2018-09-03 23:01:30",
			"result": "7,10,9,2,8,6,5,1,3,4",
			"year": 2018
		}, {
			"id": 224839314,
			"period": 701992,
			"date": "2018-09-03 22:56:30",
			"result": "2,1,5,8,9,7,6,3,10,4",
			"year": 2018
		}, {
			"id": 224836923,
			"period": 701991,
			"date": "2018-09-03 22:51:30",
			"result": "6,4,2,7,1,8,9,3,10,5",
			"year": 2018
		}, {
			"id": 224839872,
			"period": 701990,
			"date": "2018-09-03 22:46:30",
			"result": "4,2,10,1,9,7,5,6,8,3",
			"year": 2018
		}, {
			"id": 224839623,
			"period": 701989,
			"date": "2018-09-03 22:41:30",
			"result": "1,10,6,5,2,8,4,9,3,7",
			"year": 2018
		}, {
			"id": 224836667,
			"period": 701988,
			"date": "2018-09-03 22:36:30",
			"result": "2,5,1,6,4,9,8,7,3,10",
			"year": 2018
		}, {
			"id": 224840571,
			"period": 701987,
			"date": "2018-09-03 22:31:30",
			"result": "6,8,1,2,4,5,3,10,9,7",
			"year": 2018
		}
	]
}